brookie/__init__.py
brookie/brookie.py
brookie-0.0.2.dist-info/LICENSE
brookie-0.0.2.dist-info/METADATA
brookie-0.0.2.dist-info/WHEEL
brookie-0.0.2.dist-info/top_level.txt
brookie-0.0.2.dist-info/RECORD
