Metadata-Version: 2.1
Name: brookie
Version: 0.0.2
Summary: python package
Home-page: https://github.com/rlape2/brookie
Author: Robby Lape
Author-email: rlape@vols.utk.edu
License: MIT license
Keywords: brookie
Classifier: Development Status :: 2 - Pre-Alpha
Classifier: Intended Audience :: Developers
Classifier: License :: OSI Approved :: MIT License
Classifier: Natural Language :: English
Classifier: Programming Language :: Python :: 3
Classifier: Programming Language :: Python :: 3.7
Classifier: Programming Language :: Python :: 3.8
Classifier: Programming Language :: Python :: 3.9
Classifier: Programming Language :: Python :: 3.10
Requires-Python: >=3.7
License-File: LICENSE
